pykaahma_linz/ContentManager.py
pykaahma_linz/CustomErrors.py
pykaahma_linz/JobResult.py
pykaahma_linz/KItem.py
pykaahma_linz/KServer.py
pykaahma_linz/KTableItem.py
pykaahma_linz/KVectorItem.py
pykaahma_linz/__init__.py
pykaahma_linz/__version__.py
pykaahma_linz/features/Conversion.py
pykaahma_linz/features/__init__.py
pykaahma_linz/features/export.py
pykaahma_linz/features/wfs.py
pykaahma_linz-0.1.10.dist-info/licenses/LICENSE
pykaahma_linz-0.1.10.dist-info/METADATA
pykaahma_linz-0.1.10.dist-info/WHEEL
pykaahma_linz-0.1.10.dist-info/top_level.txt
pykaahma_linz-0.1.10.dist-info/RECORD
