Metadata-Version: 2.4
Name: pykaahma-linz
Version: 0.1.10
Summary: A Pythonic client for accessing and querying datasets from the LINZ Data Service.
Author-email: Paul Haakma <phaakma@gmail.com>
License-Expression: MIT
Keywords: kaahma,koordinates,LINZ,geospatial,open data,API,GIS
Requires-Python: >=3.10
License-File: LICENSE
Requires-Dist: geopandas>=1.0.1
Requires-Dist: pandas>=2.0.2
Requires-Dist: requests>=2.30.0
Requires-Dist: tenacity>=9.0.0
Requires-Dist: httpx>=0.25.0
Dynamic: license-file
